django_gbase8s/__init__.py
django_gbase8s/base.py
django_gbase8s/client.py
django_gbase8s/compiler.py
django_gbase8s/creation.py
django_gbase8s/features.py
django_gbase8s/introspection.py
django_gbase8s/operations.py
django_gbase8s/schema.py
django_gbase8s/utils.py
django_gbase8s/validation.py
django_gbase8s-4.0.0.dist-info/LICENSE
django_gbase8s-4.0.0.dist-info/METADATA
django_gbase8s-4.0.0.dist-info/WHEEL
django_gbase8s-4.0.0.dist-info/top_level.txt
django_gbase8s-4.0.0.dist-info/RECORD
