Metadata-Version: 2.1
Name: django-gbase8s
Version: 4.0.0
Summary: Django backend for GBase 8s database
Author: GBase 8s team
Project-URL: Source, https://gitee.com/GBase8s/django-gbase8s
Classifier: Framework :: Django
Classifier: Framework :: Django :: 4.0
Classifier: License :: OSI Approved :: MIT License
Classifier: Operating System :: OS Independent
Classifier: Programming Language :: Python
Classifier: Programming Language :: Python :: 3
Classifier: Programming Language :: Python :: 3.8
Requires-Python: >=3.8
License-File: LICENSE
Requires-Dist: gbase8sdb
Requires-Dist: django>=4.0.0
